core/__init__.py
core/cli.py
core/config.py
core/database.py
core/main.py
core/rate_limit.py
core/relations.yaml
core/utils.py
core/admin/__init__.py
core/admin/routes.py
core/admin/url.py
core/api/__init__.py
core/api/auth.py
core/api/comments.py
core/api/entities.py
core/api/forms.py
core/api/media.py
core/api/relations.py
core/api/revisions.py
core/api/schema.py
core/api/search.py
core/api/seo.py
core/content_types/__init__.py
core/content_types/audit_log.yaml
core/content_types/category.yaml
core/content_types/channel.yaml
core/content_types/comment.yaml
core/content_types/edit_lock.yaml
core/content_types/form.yaml
core/content_types/form_submission.yaml
core/content_types/menu_item.yaml
core/content_types/news.yaml
core/content_types/page.yaml
core/content_types/plugin.yaml
core/content_types/plugin_developer.yaml
core/content_types/plugin_review.yaml
core/content_types/post.yaml
core/content_types/redirect.yaml
core/content_types/scheduled_action.yaml
core/content_types/series.yaml
core/content_types/site_setting.yaml
core/content_types/tag.yaml
core/content_types/user.yaml
core/content_types/widget.yaml
core/content_types/workflow_history.yaml
core/engine/__init__.py
core/engine/routes.py
core/migrations/env.py
core/migrations/script.py.mako
core/migrations/versions/2038bdf6693b_add_import_jobs_table.py
core/migrations/versions/3a1b2c3d4e5f_add_file_hash_to_media.py
core/models/__init__.py
core/models/auth.py
core/models/entity.py
core/models/import_job.py
core/models/media.py
core/models/relation.py
core/models/revision.py
core/plugins/__init__.py
core/plugins/base.py
core/plugins/hooks.py
core/plugins/loader.py
core/plugins/manager.py
core/scaffold/.env.template
core/scaffold/.gitignore.template
core/scaffold/__init__.py
core/scaffold/config.yaml.template
core/scaffold/themes/default/theme.yaml
core/scaffold/themes/default/templates/archive.html
core/scaffold/themes/default/templates/base.html
core/scaffold/themes/default/templates/category.html
focomy-0.1.120.dist-info/METADATA
focomy-0.1.120.dist-info/WHEEL
focomy-0.1.120.dist-info/entry_points.txt
focomy-0.1.120.dist-info/licenses/LICENSE
focomy-0.1.120.dist-info/RECORD
