Metadata-Version: 2.4
Name: focomy
Version: 0.1.120
Summary: The Most Beautiful CMS - A metadata-driven, zero-duplicate-code content management system
Project-URL: Homepage, https://github.com/focomy/focomy
Project-URL: Documentation, https://focomy.dev/docs
Project-URL: Repository, https://github.com/focomy/focomy
Project-URL: Issues, https://github.com/focomy/focomy/issues
Author: Focomy Team
License-Expression: MIT
License-File: LICENSE
Keywords: blog,cms,content-management,fastapi,headless-cms,website
Classifier: Development Status :: 4 - Beta
Classifier: Environment :: Web Environment
Classifier: Framework :: FastAPI
Classifier: Intended Audience :: Developers
Classifier: License :: OSI Approved :: MIT License
Classifier: Operating System :: OS Independent
Classifier: Programming Language :: Python :: 3
Classifier: Programming Language :: Python :: 3.10
Classifier: Programming Language :: Python :: 3.11
Classifier: Programming Language :: Python :: 3.12
Classifier: Topic :: Internet :: WWW/HTTP :: Dynamic Content
Classifier: Topic :: Internet :: WWW/HTTP :: Site Management
Requires-Python: >=3.10
Requires-Dist: aiofiles>=23.2.0
Requires-Dist: aiohttp>=3.9.0
Requires-Dist: alembic>=1.13.0
Requires-Dist: asyncpg>=0.29.0
Requires-Dist: authlib>=1.2.0
Requires-Dist: bcrypt>=4.1.0
Requires-Dist: beautifulsoup4>=4.12.0
Requires-Dist: email-validator>=2.1.0
Requires-Dist: fastapi>=0.104.0
Requires-Dist: httpx>=0.25.0
Requires-Dist: itsdangerous>=2.1.0
Requires-Dist: jinja2>=3.1.2
Requires-Dist: pillow>=10.1.0
Requires-Dist: psycopg2-binary>=2.9.0
Requires-Dist: pydantic-settings>=2.1.0
Requires-Dist: pydantic>=2.5.0
Requires-Dist: pyotp>=2.9.0
Requires-Dist: python-jose[cryptography]>=3.3.0
Requires-Dist: python-multipart>=0.0.6
Requires-Dist: python-slugify>=8.0.1
Requires-Dist: pyyaml>=6.0.1
Requires-Dist: slowapi>=0.1.9
Requires-Dist: sqlalchemy[asyncio]>=2.0.0
Requires-Dist: structlog>=24.1.0
Requires-Dist: uvicorn[standard]>=0.24.0
Provides-Extra: all
Requires-Dist: redis>=5.0.0; extra == 'all'
Provides-Extra: dev
Requires-Dist: black>=23.0.0; extra == 'dev'
Requires-Dist: mypy>=1.7.0; extra == 'dev'
Requires-Dist: pytest-asyncio>=0.21.0; extra == 'dev'
Requires-Dist: pytest-cov>=4.1.0; extra == 'dev'
Requires-Dist: pytest>=7.4.0; extra == 'dev'
Requires-Dist: ruff>=0.1.0; extra == 'dev'
Provides-Extra: redis
Requires-Dist: redis>=5.0.0; extra == 'redis'
